setup.py
extheano/__init__.py
extheano/jit.py
extheano/nodebuffer.py
extheano.egg-info/PKG-INFO
extheano.egg-info/SOURCES.txt
extheano.egg-info/dependency_links.txt
extheano.egg-info/top_level.txt