Metadata-Version: 1.1
Name: extheano
Version: 0.1.1
Summary: Small package providing an easy access to Theano, a scientific library for efficient computations
Home-page: https://github.com/koheimiya/extheano
Author: Kohei Miyaguchi
Author-email: koheimiyaguchi@gmail.com
License: MIT License
Platform: UNKNOWN
Classifier: Intended Audience :: Developers
Classifier: Intended Audience :: Science/Research
Classifier: Operating System :: OS Independent
Classifier: Programming Language :: Python
Classifier: Programming Language :: Python :: 3.3
Classifier: Topic :: Utilities
Classifier: License :: OSI Approved :: MIT License
